mongodb_connector/__init__.py
mongodb_connector/lark_sql.py
mongodb_connector/mongodb_connector.py
mongodb_connector/simple_sql.lark
mongodb_connector-0.2.0.dist-info/LICENSE
mongodb_connector-0.2.0.dist-info/WHEEL
mongodb_connector-0.2.0.dist-info/METADATA
mongodb_connector-0.2.0.dist-info/RECORD
