Metadata-Version: 2.1
Name: mongodb-connector
Version: 0.2.0
Summary: 
Author: Your Name
Author-email: you@example.com
Requires-Python: >=3.7
Classifier: Programming Language :: Python :: 3
Classifier: Programming Language :: Python :: 3.7
Classifier: Programming Language :: Python :: 3.8
Requires-Dist: lark-parser (>=0.12.0)
Requires-Dist: pymongo (>=4.0.1)
